{"start_hierarchy": 2, "goal_hierarchy": 1, "optimal_cost": 5, "num_generated_nodes": 9, "num_expanded_nodes": 5, "num_sols": 2, "search_depth": 0.0, "alter_move": 2.3, "suboptimal_path(detour)": 0.0, "suboptimal_path(deadend)": 0.16666666666666666, "conflict_move": 0.0, "optimal_cost(greedy)": 5, "num_generated_nodes(greedy)": 9, "num_expanded_nodes(greedy)": 5, "optimal_cost(greedy_gc)": 5, "num_generated_nodes(greedy_gc)": 11, "num_expanded_nodes(greedy_gc)": 6, "optimal_cost(gc)": 5, "num_generated_nodes(gc)": 15, "num_expanded_nodes(gc)": 10, "optimal_cost(ol)": 2, "num_nodes(ol)": 7, "num_nodes(BrFS)": 227, "num_nodes(DFS)": 26, "optimal_cost(ol_new)": 1, "num_nodes(ol_new)": 6, "heuristic_timing": 1.9417475728155336, "agent_timing": 1.7, "model_time": 26, "score": -1.756, "init_pos": [[1, 2, 3], [0, 0], [0]], "goal_pos": [[2, 1, 0], [3, 0], [0]], "rt_full": 6525.0, "rt_default": 3178.5, "sol_length(BFS)": 10, "num_expanded_nodes(BFS)": 34, "sol_length(DFS)": 26, "num_expanded_nodes(DFS)": 30, "sol_length(astar+gc)": 10, "num_expanded_nodes(astar+gc)": 17, "sol_length(greedy+gc)": 10, "num_expanded_nodes(greedy+gc)": 14}